YunshangJiasuYingjieZhongguoHulianwangXinZhouqi/README.md
YunshangJiasuYingjieZhongguoHulianwangXinZhouqi/__init__.py
YunshangJiasuYingjieZhongguoHulianwangXinZhouqi/__main__.py
YunshangJiasuYingjieZhongguoHulianwangXinZhouqi/file.pdf
YunshangJiasuYingjieZhongguoHulianwangXinZhouqi/index.html
yunshang_jiasu_yingjie_zhongguo_hulianwang_xin_zhouqi-2024.3.6.0.dist-info/METADATA
yunshang_jiasu_yingjie_zhongguo_hulianwang_xin_zhouqi-2024.3.6.0.dist-info/WHEEL
yunshang_jiasu_yingjie_zhongguo_hulianwang_xin_zhouqi-2024.3.6.0.dist-info/entry_points.txt
yunshang_jiasu_yingjie_zhongguo_hulianwang_xin_zhouqi-2024.3.6.0.dist-info/top_level.txt
yunshang_jiasu_yingjie_zhongguo_hulianwang_xin_zhouqi-2024.3.6.0.dist-info/RECORD
